{
  "examId": "107-a",
  "examTitle": "제107회 전산회계 2급 A형",
  "year": 2023,
  "round": 107,
  "questions": [
    {
      "id": "107-a-1",
      "number": 1,
      "subject": "2023년 이론",
      "question": "다음 중 회계상 거래에 해당하는 것은?",
      "choices": [
        "판매점 확장을 위하여 직원을 채용하고 근로계약서를 작성하다.",
        "사업확장을 위하여 은행에서 운영자금을 차입하기로 결정하다.",
        "재고 부족이 예상되어 판매용 상품을 추가로 주문하다.",
        "당사 데이터센터의 화재로 인하여 서버용 PC가 소실되다."
      ],
      "answer": 4
    },
    {
      "id": "107-a-2",
      "number": 2,
      "subject": "2023년 이론",
      "question": "다음 중 거래요소의 결합 관계가 잘못 짝지어진 것은?",
      "choices": [
        "(차) / 자본의 감소 / (대) / 자산의 증가",
        "(차) / 수익의 소멸 / (대) / 자산의 감소",
        "(차) / 비용의 발생 / (대) / 부채의 증가",
        "(차) / 부채의 감소 / (대) / 자본의 증가"
      ],
      "answer": 2
    },
    {
      "id": "107-a-3",
      "number": 3,
      "subject": "2023년 이론",
      "question": "다음의 거래 중 비용이 발생하지 않는 것은?",
      "choices": [
        "업무용 자동차에 대한 당기분 자동차세 100,000원을 현금으로 납부하다.",
        "적십자회비 100,000원을 현금으로 납부하다.",
        "상공회의소 회비 100,000원을 현금으로 납부하다.",
        "전월에 급여 지급 시 원천징수한 근로소득세를 현금으로 납부하다."
      ],
      "answer": 4
    },
    {
      "id": "107-a-4",
      "number": 4,
      "subject": "2023년 이론",
      "question": "다음 계정과목 중 증가 시 재무상태표상 대변 항목이 아닌 것은?",
      "choices": [
        "자본금",
        "선수이자",
        "선급금",
        "외상매입금"
      ],
      "answer": 3
    },
    {
      "id": "107-a-5",
      "number": 5,
      "subject": "2023년 이론",
      "question": "다음의 자료에서 당좌자산의 합계액은 얼마인가? ㆍ현금 300,000원 ㆍ외상매출금 200,000원 ㆍ보통예금 800,000원 ㆍ단기매매증권 500,000원 ㆍ외상매입금 400,000원",
      "choices": [
        "1,700,000원",
        "1,800,000원",
        "2,000,000원",
        "2,200,000원"
      ],
      "answer": 1
    },
    {
      "id": "107-a-6",
      "number": 6,
      "subject": "2023년 이론",
      "question": "다음 자료에서 설명하는 계정과목으로 옳은 것은? 상품 판매대금을 조기에 수취함에 따른 계약상 약정에 의한 일정 대금의 할인",
      "choices": [
        "매출채권처분손실",
        "매출환입",
        "매출할인",
        "매출에누리"
      ],
      "answer": 1
    },
    {
      "id": "107-a-7",
      "number": 7,
      "subject": "2023년 이론",
      "question": "다음 중 일반적인 상거래에서 발생한 것으로 아직 회수되지 않은 경우의 회계처리 시 계정과목으로 올바른 것은?",
      "choices": [
        "미수수익",
        "선수수익",
        "미수금",
        "외상매출금"
      ],
      "answer": 4
    },
    {
      "id": "107-a-8",
      "number": 8,
      "subject": "2023년 이론",
      "question": "다음 자료에서 기말자본은 얼마인가? ㆍ기초자본 1,000,000원 ㆍ총비용 5,000,000원 ㆍ총수익 8,000,000원",
      "choices": [
        "2,000,000원",
        "3,000,000원",
        "4,000,000원",
        "8,000,000원"
      ],
      "answer": 4
    },
    {
      "id": "107-a-9",
      "number": 9,
      "subject": "2023년 이론",
      "question": "다음은 당기 손익계산서의 일부를 발췌한 자료이다. 당기 매출액을 구하시오. 매출액 기초상품재고액 당기총매입액 기말상품재고액 매출총이익 ? 원 25,000,000원 168,000,000원 15,000,000원 172,000,000원",
      "choices": [
        "350,000,000원",
        "370,000,000원",
        "372,000,000원",
        "382,000,000원"
      ],
      "answer": 2
    },
    {
      "id": "107-a-10",
      "number": 10,
      "subject": "2023년 이론",
      "question": "다음 자료의 ( ) 안에 들어갈 계정과목으로 가장 적절한 것은? ( )은 기업의 주된 영업활동인 상품 등을 판매하고 이에 대한 대금으로 상대방으로부터 수취한 어음이다.",
      "choices": [
        "지급어음",
        "받을어음",
        "외상매출금",
        "선수금"
      ],
      "answer": 2
    },
    {
      "id": "107-a-11",
      "number": 11,
      "subject": "2023년 이론",
      "question": "다음은 차량운반구의 처분과 관련된 자료이다. 차량운반구의 처분가액은 얼마인가? ㆍ취득가액：16,000,000원 ㆍ감가상각누계액：9,000,000원 ㆍ유형자산처분손실：1,000,000원",
      "choices": [
        "6,000,000원",
        "7,000,000원",
        "8,000,000원",
        "14,000,000원"
      ],
      "answer": 1
    },
    {
      "id": "107-a-12",
      "number": 12,
      "subject": "2023년 이론",
      "question": "다음 중 일정 시점의 재무상태를 나타내는 재무보고서의 계정과목으로만 짝지어진 것이 아닌 것은?",
      "choices": [
        "외상매입금, 선수금 / 임대료, 이자비용",
        "선급금, 외상매출금 / 선수금, 보통예금"
      ],
      "answer": 2
    },
    {
      "id": "107-a-13",
      "number": 13,
      "subject": "2023년 이론",
      "question": "다음 중 아래의 빈칸에 들어갈 내용으로 적절한 것은? 현금및현금성자산은 통화 및 타인발행수표 등 통화대용증권과 당좌예금, 보통예금 및 큰 거래비용 없이 현금으로 전환이 용이하고, 이자율 변동에 따른 가치변동의 위험이 경미한 금융상품으로서 취득 당시 만기일 또는 상환일이 ( ) 이내인 것을 말한다.",
      "choices": [
        "1개월",
        "2개월",
        "3개월",
        "6개월"
      ],
      "answer": 3
    },
    {
      "id": "107-a-14",
      "number": 14,
      "subject": "2023년 이론",
      "question": "재고자산의 단가 결정방법 중 아래의 자료에서 설명하는 특징을 가진 것은? ㆍ실제 물량 흐름과 유사하다. ㆍ현행수익에 과거원가가 대응된다. ㆍ기말재고가 가장 최근에 매입한 상품의 단가로 계상된다.",
      "choices": [
        "선입선출법",
        "후입선출법",
        "총평균법",
        "개별법"
      ],
      "answer": 1
    },
    {
      "id": "107-a-15",
      "number": 15,
      "subject": "2023년 이론",
      "question": "다음 중 영업외수익에 해당하는 항목으로 적절한 것은?",
      "choices": [
        "미수수익",
        "경상개발비",
        "외환차손",
        "이자수익"
      ],
      "answer": 2
    }
  ]
}
