{
  "examId": "121-a",
  "examTitle": "제121회 전산회계 2급 A형",
  "year": 2025,
  "round": 121,
  "questions": [
    {
      "id": "121-a-1",
      "number": 1,
      "subject": "2025년 이론",
      "question": "다음 중 재무회계의 특징으로 옳지 않은 것은?",
      "choices": [
        "내부통제 목적으로 이용된다.",
        "일반기업회계기준에 의해 작성된다.",
        "기본가정으로 기업실체, 계속기업, 기간별보고를 들 수 있다.",
        "기업 외부 이해관계자의 경제적 의사결정에 유용한 정보를 제공하는 것을 목적으로 한다."
      ],
      "answer": 1
    },
    {
      "id": "121-a-2",
      "number": 2,
      "subject": "2025년 이론",
      "question": "다음 중 시산표 등식으로 옳은 것은?",
      "choices": [
        "기말자산＋총수익＝기말부채＋기초자본＋총비용",
        "기말자산＋총수익＝기말부채＋기말자본＋총비용",
        "기말자산＋총비용＝기말부채＋기초자본＋총수익",
        "기말자산＋총비용＝기말부채＋기말자본＋총수익"
      ],
      "answer": 3
    },
    {
      "id": "121-a-3",
      "number": 3,
      "subject": "2025년 이론",
      "question": "다음의 자료를 통해 외상매출금의 당기 입금액을 계산하면 얼마인가? ㆍ기초 외상매출금：100,000원 ㆍ기말 외상매출금：80,000원 ㆍ당기 외상매출액：300,000원 ㆍ매출에누리 및 매출할인：30,000원",
      "choices": [
        "90,000원",
        "290,000원",
        "350,000원",
        "450,000원"
      ],
      "answer": 2
    },
    {
      "id": "121-a-4",
      "number": 4,
      "subject": "2025년 이론",
      "question": "다음의 자료에서 주식의 매입거래에서 지출한 수수료에 대한 회계처리로 옳은 것은? ㆍ단기 시세차익을 목적으로 시장성이 있는 상장 주식 100주(1주당 액면 금액 5,000원)를 1주당 7,000원 에 구입하고, 대금은 수수료 10,000원과 함께 현금으로 지급하였다.",
      "choices": [
        "이자비용으로 처리한다.",
        "수수료비용으로 처리한다.",
        "단기매매증권의 취득원가에 가산한다.",
        "단기매매증권의 취득원가에서 차감한다."
      ],
      "answer": 2
    },
    {
      "id": "121-a-5",
      "number": 5,
      "subject": "2025년 이론",
      "question": "다음 중 기말재고에 적용할 취득단가 산정 시 원가흐름의 가정으로 적용하는 방법이 아닌 것은?",
      "choices": [
        "선입선출법",
        "후입선출법",
        "정액법",
        "이동평균법"
      ],
      "answer": 3
    },
    {
      "id": "121-a-6",
      "number": 6,
      "subject": "2025년 이론",
      "question": "다음 중 차량판매업을 영위하는 회사의 감가상각자산에 해당하는 것은?",
      "choices": [
        "토지",
        "판매용 차량운반구",
        "투자를 목적으로 보유하는 건물",
        "사무실 냉난방기"
      ],
      "answer": 4
    },
    {
      "id": "121-a-7",
      "number": 7,
      "subject": "2025년 이론",
      "question": "다음의 자료를 이용하여 당기 중에 처분한 비품의 취득원가를 계산하면 얼마인가? ㆍ비품 처분가액：1,000,000원 ㆍ비품 감가상각누계액：1,800,000원 ㆍ비품 유형자산처분이익：100,000원",
      "choices": [
        "2,500,000원",
        "2,600,000원",
        "2,700,000원",
        "2,800,000원"
      ],
      "answer": 3
    },
    {
      "id": "121-a-8",
      "number": 8,
      "subject": "2025년 이론",
      "question": "다음 중 자산에 해당하는 계정과목은 모두 몇 개인가? ㆍ단기대여금 ㆍ선급비용 ㆍ매출채권 ㆍ임차보증금 ㆍ미수금 ㆍ선급금 ㆍ선수금 ㆍ예수금",
      "choices": [
        "4개",
        "5개",
        "6개",
        "7개"
      ],
      "answer": 3
    },
    {
      "id": "121-a-9",
      "number": 9,
      "subject": "2025년 이론",
      "question": "다음 중 비유동 부채에 해당하는 계정과목이 아닌 것은? ㄱ. 선수금 ㄴ. 단기차입금 ㄷ. 장기미지급금 ㄹ. 퇴직급여충당부채",
      "choices": [
        "ㄱ, ㄴ",
        "ㄱ, ㄹ",
        "ㄴ, ㄷ",
        "ㄷ, ㄹ"
      ],
      "answer": 1
    },
    {
      "id": "121-a-10",
      "number": 10,
      "subject": "2025년 이론",
      "question": "다음 중 손익계산서의 계정과목으로만 짝지어진 것은?",
      "choices": [
        "자본금, 보통예금",
        "상품매출, 예수금",
        "이자수익, 감가상각비",
        "대손충당금, 이자비용"
      ],
      "answer": 3
    },
    {
      "id": "121-a-11",
      "number": 11,
      "subject": "2025년 이론",
      "question": "다음의 자료는 2025년 12월 31일 현재 각 계정의 잔액이다. 단기차입금을 계산하면 얼마인가? ㆍ현금：550,000원 ㆍ선수금：200,000원 ㆍ자본금：500,000원 ㆍ외상매출금：250,000원 ㆍ선급금：500,000원 ㆍ단기차입금：?",
      "choices": [
        "500,000원",
        "600,000원",
        "700,000원",
        "800,000원"
      ],
      "answer": 2
    },
    {
      "id": "121-a-12",
      "number": 12,
      "subject": "2025년 이론",
      "question": "기말 창고에 재고자산이 100,000원이지만 회계담당자의 실수로 재무상태표에는 90,000원으로 계상되었다. 회계담당자의 실수가 재무제표에 미치는 영향으로 옳지 않은 것은?",
      "choices": [
        "기말재고자산이 10,000원 과소계상 되었다.",
        "매출원가는 10,000원 과소계상 되었다.",
        "매출총이익이 10,000원 과소계상 되었다.",
        "영업이익이 10,000원 과소계상 되었다."
      ],
      "answer": 2
    },
    {
      "id": "121-a-13",
      "number": 13,
      "subject": "2025년 이론",
      "question": "다음은 한국상사의 현금과부족 자료이다. 결산 시 현금과부족 계정 잔액의 원인이 밝혀지지 않았다. 결산 시 계정과목과 금액으로 옳은 것은? 단, 회계기간은 1월 1일부터 12월 31일까지이다. ※ 현금 관련 자료 현금과부족 7/1 이 자 수 익 60,000 1/30 현 금 80,000 12/31 ( 가 ) ( 나 ) 80,000 80,000 ( 가 ) ( 나 )",
      "choices": [
        "잡이익 / 20,000원",
        "이자수익 / 20,000원",
        "잡손실 / 20,000원",
        "이자비용 / 20,000원"
      ],
      "answer": 1
    },
    {
      "id": "121-a-14",
      "number": 14,
      "subject": "2025년 이론",
      "question": "31. (차) 현금과부족 20,000원 (대) 잡이익 20,000원 ㆍ12월 31일 원인이 밝혀지지 않은 잔액 20,000원",
      "choices": [
        "이자수익",
        "이자비용",
        "매출원가",
        "잡이익"
      ],
      "answer": 3
    },
    {
      "id": "121-a-15",
      "number": 15,
      "subject": "2025년 이론",
      "question": "다음 중 영업이익에 영향을 미치는 계정으로 옳은 것은?",
      "choices": [
        "이자수익",
        "이자비용",
        "매출원가",
        "잡이익"
      ],
      "answer": 2
    }
  ]
}
